<?xml version="1.0" encoding="utf-8"?>
<!DOCTYPE hibernate-mapping PUBLIC "-//Hibernate/Hibernate Mapping DTD 3.0//EN"
"http://hibernate.sourceforge.net/hibernate-mapping-3.0.dtd">
<!-- 
    Mapping file autogenerated by MyEclipse Persistence Tools
-->
<hibernate-mapping>
    <class name="com.zxt.compplatform.codegenerate.entity.EngCodeLog" table="ENG_CODE_LOG" >
        <composite-id>
            <key-property name="codeVersionId" type="java.lang.String">
                <column name="CODE_VERSION_ID" length="64" />
            </key-property>
            <key-property name="codeFormsId" type="java.lang.String">
                <column name="CODE_FORMS_ID" length="64" />
            </key-property>
        </composite-id>
        <property name="codeUserId" type="java.lang.Long">
            <column name="CODE_USER_ID" precision="22" scale="0" />
        </property>
        <property name="codePath" type="java.lang.String">
            <column name="CODE_PATH" length="400" />
        </property>
        <property name="codeCreateTime" type="java.util.Date">
            <column name="CODE_CREATE_TIME" length="7" />
        </property>
        <property name="codeAllFile" type="java.lang.String">
            <column name="CODE_ALL_FILE" length="4000" />
        </property>
        <property name="codeRemark" type="java.lang.String">
            <column name="CODE_REMARK" length="4000" />
        </property>
    </class>
</hibernate-mapping>
